scipy_sugar/__init__.py
scipy_sugar/stats/__init__.py
scipy_sugar/stats/_normalize.py
scipy_sugar/stats/test/test_normalize.py
scipy_sugar-1.0.2.dist-info/DESCRIPTION.rst
scipy_sugar-1.0.2.dist-info/METADATA
scipy_sugar-1.0.2.dist-info/RECORD
scipy_sugar-1.0.2.dist-info/WHEEL
scipy_sugar-1.0.2.dist-info/metadata.json
scipy_sugar-1.0.2.dist-info/top_level.txt
scipy_sugar-1.0.2.dist-info/zip-safe
