Metadata-Version: 2.0
Name: scipy-sugar
Version: 1.0.2
Summary: Missing SciPy functionalities.
Home-page: https://github.com/limix/scipy-sugar
Author: Danilo Horta
Author-email: horta@ebi.ac.uk
License: MIT
Platform: UNKNOWN
Classifier: Development Status :: 5 - Production/Stable
Classifier: License :: OSI Approved :: MIT License
Classifier: Operating System :: OS Independent
Requires-Dist: numpy (>=1.9)
Requires-Dist: scipy (>=0.18)
